README.md
active_sqlalchemy.py
setup.py
Active_SQLAlchemy.egg-info/PKG-INFO
Active_SQLAlchemy.egg-info/SOURCES.txt
Active_SQLAlchemy.egg-info/dependency_links.txt
Active_SQLAlchemy.egg-info/pbr.json
Active_SQLAlchemy.egg-info/requires.txt
Active_SQLAlchemy.egg-info/top_level.txt