Metadata-Version: 1.1
Name: Active-SQLAlchemy
Version: 0.3.5
Summary: 
